uniparser_yawarana/__init__.py
uniparser_yawarana/data/bad_analyses.txt
uniparser_yawarana/data/clitics.txt
uniparser_yawarana/data/derivations.txt
uniparser_yawarana/data/disambiguation.cg3
uniparser_yawarana/data/etym_lookup.yaml
uniparser_yawarana/data/lex_rules.txt
uniparser_yawarana/data/lexemes.txt
uniparser_yawarana/data/paradigms.txt
uniparser_yawarana-0.0.6.dist-info/LICENSE
uniparser_yawarana-0.0.6.dist-info/METADATA
uniparser_yawarana-0.0.6.dist-info/WHEEL
uniparser_yawarana-0.0.6.dist-info/top_level.txt
uniparser_yawarana-0.0.6.dist-info/RECORD
